{
  "layout_type": "Featured",
  "reasoning": "Gluegun은 Node.js 기반 CLI 개발을 위한 포괄적인 도구 모음으로, 파일 시스템 조작, API 연동, 사용자 입력 처리 등 다양한 기능을 제공하여 개발 생산성을 크게 향상시킵니다.",
  "score": 8,
  "summary": "Gluegun은 Node.js 기반 CLI 개발을 위한 TypeScript/JavaScript 프레임워크입니다. 파라미터 처리, 파일 템플릿 생성, 파일 시스템 조작, 외부 스크립트 실행, API 연동, 사용자 프롬프트, 색상/테이블 출력, 버전 관리, 문자열 처리 등 다양한 기능을 제공합니다. 또한 플러그인 및 확장 기능을 통해 생태계를 확장할 수 있습니다.",
  "tags": [
    "CLI",
    "Node.js",
    "TypeScript"
  ],
  "title_ko": "Node.js CLI 개발 생산성을 높이는 Gluegun 프레임워크",
  "url": "https://github.com/infinitered/gluegun",
  "source_id": "geeknews_new",
  "crawled_at": "2025-12-04T15:28:17.635710",
  "original_title": "infinitered/gluegun: A delightful toolkit for building TypeScript-powered command-line apps."
}