{
  "layout_type": "Standard",
  "reasoning": "The article presents a nuanced perspective on engineering roles, contrasting two distinct operating environments within large tech companies, making it suitable for a standard display.",
  "score": 7,
  "summary": "엔지니어링 역할에 대한 두 가지 상반된 운영 환경을 제시하며, 외부 고객 대상 제품 개발과 내부 개발자 도구 및 인프라 팀의 차이를 분석합니다. 외부 제품 팀은 분기별 목표 변화와 빠른 속도에 최적화된 '스포트라이트' 전략을 따르는 반면, 내부 팀은 엔지니어 고객의 피드백을 바탕으로 장기적인 '시스템'과 '스튜어드십'에 집중합니다. 이러한 환경적 차이가 엔지니어의 업무 방식과 성공 측정 기준에 근본적인 영향을 미칩니다.",
  "tags": [
    "Software Engineering",
    "Career Development",
    "Tech Leadership"
  ],
  "title_ko": "스포트라이트 vs. 시스템: 대규모 기술 기업 엔지니어링 역할의 두 가지 길",
  "url": "https://lalitm.com/software-engineering-outside-the-spotlight/",
  "source_id": "hackernews_rss",
  "crawled_at": "2025-12-05T13:43:16.117907",
  "original_title": "Why I Ignore The Spotlight as a Staff Engineer"
}